seittik/__init__.py
seittik/pipes.py
seittik/shears.py
seittik/utils/__init__.py
seittik/utils/abc.py
seittik/utils/argutils.py
seittik/utils/classutils.py
seittik/utils/collections.py
seittik/utils/compareutils.py
seittik/utils/diceutils.py
seittik/utils/flatten.py
seittik/utils/funcutils.py
seittik/utils/merge.py
seittik/utils/randutils.py
seittik/utils/sentinels.py
seittik/utils/stringutils.py
seittik/utils/structutils.py
seittik/utils/walk.py
seittik-2023.4.dist-info/LICENSE
seittik-2023.4.dist-info/METADATA
seittik-2023.4.dist-info/WHEEL
seittik-2023.4.dist-info/RECORD
