Metadata-Version: 2.1
Name: seittik
Version: 2023.4
Summary: A functional programming library that aims to supplant Python's existing functional interfaces, offering a more comprehensive and expressive alternative.
License: MIT
Keywords: functional,functools,iterable,iteration,iterator,itertools,lambda,pipe,shear
Author: Tom Tobin
Author-email: opensource@alchemicalhydra.com
Requires-Python: >=3.10,<4.0
Classifier: Development Status :: 3 - Alpha
Classifier: Environment :: Console
Classifier: Intended Audience :: Developers
Classifier: License :: OSI Approved :: MIT License
Classifier: Natural Language :: English
Classifier: Programming Language :: Python
Classifier: Programming Language :: Python :: 3
Classifier: Programming Language :: Python :: 3.10
Classifier: Programming Language :: Python :: 3.11
Classifier: Programming Language :: Python :: 3
Classifier: Programming Language :: Python :: 3 :: Only
Classifier: Programming Language :: Python :: 3.10
Classifier: Programming Language :: Python :: 3.11
Classifier: Topic :: Software Development :: Libraries
Classifier: Topic :: Software Development :: Libraries :: Python Modules
Project-URL: Changelog, https://seittik.com/changelog.html
Project-URL: Documentation, https://seittik.com/
Project-URL: Homepage, https://seittik.com/
Project-URL: Issue Tracker, https://github.com/alchemicalhydra/seittik/issues
Project-URL: Source Code, https://github.com/alchemicalhydra/seittik
